[{"id":"seanbairstow_01","first":"Sean","last":"Bairstow","3pa":7,"3pm":5,"p3":0.7143},{"id":"huntererickson_01","first":"Hunter","last":"Erickson","3pa":5,"3pm":3.3333,"p3":0.6667},{"id":"jaxonbrenchley_01","first":"Jaxon","last":"Brenchley","3pa":6,"3pm":4,"p3":0.6667},{"id":"evantroy_01","first":"Evan","last":"Troy","3pa":7,"3pm":4,"p3":0.5714},{"id":"connorharding_01","first":"Connor","last":"Harding","3pa":6,"3pm":3.3333,"p3":0.5556},{"id":"isaiahwright_01","first":"Isaiah","last":"Wright","3pa":4.6667,"3pm":2.3333,"p3":0.5},{"id":"colbyleifson_01","first":"Colby","last":"Leifson","3pa":17,"3pm":8.5,"p3":0.5},{"id":"jarrellbrantley_01","first":"Jarrell","last":"Brantley","3pa":6,"3pm":3,"p3":0.5},{"id":"nickcovington_01","first":"Nick","last":"Covington","3pa":5.3333,"3pm":2.6667,"p3":0.5},{"id":"neemanamdar_01","first":"Neema","last":"Namdar","3pa":10.3333,"3pm":5,"p3":0.4839}]
