[{"id":"davidjenkins_01","first":"David","last":"Jenkins","pts":40},{"id":"rayjontucker_01","first":"Rayjon","last":"Tucker","pts":39.5},{"id":"seanbairstow_01","first":"Sean","last":"Bairstow","pts":32},{"id":"zahirporter_01","first":"Zahir","last":"Porter","pts":30.5714},{"id":"parkervan dyke_01","first":"Parker","last":"Van Dyke","pts":30.2},{"id":"rileybattin_01","first":"Riley","last":"Battin","pts":29.6667},{"id":"bothgach_01","first":"Both","last":"Gach","pts":29},{"id":"jarrellbrantley_01","first":"Jarrell","last":"Brantley","pts":29},{"id":"reygallegos_01","first":"Rey","last":"Gallegos","pts":29},{"id":"keepalmore_01","first":"Kee","last":"Palmore","pts":29}]
