[{"team":"Egan","team_id":"EGN","ppg":96.3,"treb":41.3,"ast":16.8,"fga":91.2,"fgm":39.2,"fgp":43,"thpa":32.8,"thpm":10.2,"thpp":31.1,"fta":12.2,"ftm":7.8,"ftp":63.9,"oreb":8.8,"dreb":32.5,"stl":6,"blk":1.4,"tov":9.8,"pf":14.8},{"team":"Covington","team_id":"CVN","ppg":107.2,"treb":45.8,"ast":20.2,"fga":88.8,"fgm":39.2,"fgp":44.1,"thpa":35.4,"thpm":12,"thpp":33.9,"fta":24,"ftm":16.8,"ftp":70,"oreb":14.2,"dreb":31.6,"stl":10,"blk":3.8,"tov":16.3,"pf":19},{"team":"Drisdom","team_id":"DDM","ppg":101.6,"treb":42.8,"ast":23.6,"fga":83.6,"fgm":36.8,"fgp":44,"thpa":45.4,"thpm":14.4,"thpp":31.7,"fta":17.8,"ftm":13.6,"ftp":76.4,"oreb":10,"dreb":32.8,"stl":5,"blk":2.6,"tov":10,"pf":17.8},{"team":"Bullock","team_id":"BUL","ppg":110.7,"treb":46.8,"ast":15.7,"fga":93.5,"fgm":43.8,"fgp":46.8,"thpa":25,"thpm":8.2,"thpp":32.8,"fta":22.2,"ftm":14.8,"ftp":66.7,"oreb":12.7,"dreb":34.2,"stl":5,"blk":2.6,"tov":12,"pf":14.8},{"team":"Erickson","team_id":"ERK","ppg":108.2,"treb":43.8,"ast":22.5,"fga":93.5,"fgm":41.2,"fgp":44.1,"thpa":42.8,"thpm":15.2,"thpp":35.5,"fta":16.2,"ftm":10.5,"ftp":64.8,"oreb":13,"dreb":30.8,"stl":11.8,"blk":3,"tov":11.2,"pf":18.2},{"team":"Joyce","team_id":"JYC","ppg":111.6,"treb":46.8,"ast":25.2,"fga":92,"fgm":44.6,"fgp":48.5,"thpa":40,"thpm":14,"thpp":35,"fta":12.4,"ftm":8.4,"ftp":67.7,"oreb":10.2,"dreb":36.6,"stl":6.6,"blk":3.8,"tov":10.8,"pf":9.8},{"team":"Berger","team_id":"BGR","ppg":127,"treb":47.4,"ast":30.2,"fga":92,"fgm":50.4,"fgp":54.8,"thpa":38.2,"thpm":15.8,"thpp":41.4,"fta":13.6,"ftm":10.4,"ftp":76.5,"oreb":12.2,"dreb":35.2,"stl":8.2,"blk":3.5,"tov":11.8,"pf":12},{"team":"Stan","team_id":"STN","ppg":102.8,"treb":37.8,"ast":14.5,"fga":93.5,"fgm":40.2,"fgp":43,"thpa":36.5,"thpm":11,"thpp":30.1,"fta":18.2,"ftm":11.2,"ftp":61.5,"oreb":9.8,"dreb":28,"stl":7.5,"blk":2,"tov":5.3,"pf":14},{"team":"Humpherys","team_id":"HMP","ppg":104,"treb":41.5,"ast":11.5,"fga":88.8,"fgm":40.2,"fgp":45.3,"thpa":32.8,"thpm":10,"thpp":30.5,"fta":21.2,"ftm":13.5,"ftp":63.7,"oreb":10.5,"dreb":31,"stl":5.5,"blk":2.8,"tov":10.2,"pf":17}]
